turta_relayuhat/Turta_Relay.py
turta_relayuhat/__init__.py
turta_relayuhat-1.0.0.dist-info/LICENSE
turta_relayuhat-1.0.0.dist-info/METADATA
turta_relayuhat-1.0.0.dist-info/WHEEL
turta_relayuhat-1.0.0.dist-info/top_level.txt
turta_relayuhat-1.0.0.dist-info/RECORD
